github_backup/__init__.py
github_backup/backup.py
github_backup/cli.py
github_backup/db.py
github_backup_tool-0.0.5.dist-info/LICENSE
github_backup_tool-0.0.5.dist-info/METADATA
github_backup_tool-0.0.5.dist-info/WHEEL
github_backup_tool-0.0.5.dist-info/entry_points.txt
github_backup_tool-0.0.5.dist-info/top_level.txt
github_backup_tool-0.0.5.dist-info/RECORD
