Metadata-Version: 2.1
Name: github-backup-tool
Version: 0.0.5
Summary: A tool for backing up repositories from GitHub organizations
Home-page: https://github.com/bitsbeats/github-backup-tool
Author: thomann.io
Author-email: python@thomann.io
License: UNKNOWN
Project-URL: Bug Tracker, https://github.com/bitsbeats/github-backup-tool/issues
Platform: UNKNOWN
Classifier: Development Status :: 4 - Beta
Classifier: Programming Language :: Python :: 3
Classifier: License :: OSI Approved :: Apache Software License
Classifier: Operating System :: POSIX :: Linux
Requires-Python: >=3.6
License-File: LICENSE
Requires-Dist: GitPython
Requires-Dist: humanize
Requires-Dist: PyGithub
Requires-Dist: PyYAML
Requires-Dist: SQLAlchemy
